Metadata-Version: 2.0
Name: itchatmp
Version: 0.0.17
Summary: A complete wechat massive platform api
Home-page: https://github.com/littlecodersh/itchatmp
Author: LittleCoder
Author-email: i7meavnktqegm1b@qq.com
License: MIT
Keywords: wechat itchatmp api weixin massive platfrom
Platform: UNKNOWN
Classifier: Development Status :: 3 - Alpha
Classifier: Intended Audience :: Developers
Classifier: Topic :: Software Development :: Libraries :: Python Modules
Classifier: License :: OSI Approved :: MIT License
Classifier: Programming Language :: Python :: 2
Classifier: Programming Language :: Python :: 3
Requires-Dist: cryptography
Requires-Dist: futures
Requires-Dist: requests
Requires-Dist: tornado
